yt_aspect/__init__.py
yt_aspect/_utilities.py
yt_aspect/api.py
yt_aspect/data_structures.py
yt_aspect/fields.py
yt_aspect/io.py
yt_aspect/util.py
yt_aspect/_pvtu_test_data/__init__.py
yt_aspect-0.2.1.dist-info/LICENSE
yt_aspect-0.2.1.dist-info/METADATA
yt_aspect-0.2.1.dist-info/WHEEL
yt_aspect-0.2.1.dist-info/entry_points.txt
yt_aspect-0.2.1.dist-info/top_level.txt
yt_aspect-0.2.1.dist-info/RECORD
