Metadata-Version: 2.1
Name: yt_aspect
Version: 0.2.1
Summary: A yt plugin for loading ASPECT output
Author-email: Chris Havlin <chris.havlin@gmail.com>
Project-URL: Homepage, https://github.com/data-exp-lab/yt_aspect
Project-URL: Bug Tracker, https://github.com/data-exp-lab/yt_aspect/issues
Classifier: Programming Language :: Python :: 3
Classifier: Programming Language :: Python :: 3.9
Classifier: Programming Language :: Python :: 3.10
Classifier: Programming Language :: Python :: 3.11
Classifier: Programming Language :: Python :: 3.12
Classifier: License :: OSI Approved :: MIT License
Classifier: Operating System :: OS Independent
Requires-Python: >=3.9
License-File: LICENSE
Requires-Dist: yt >=4.2.2
Requires-Dist: xmltodict
Provides-Extra: dev
Requires-Dist: pre-commit ; extra == 'dev'
Provides-Extra: test
Requires-Dist: pytest >=6.1 ; extra == 'test'
Requires-Dist: tomli ; extra == 'test'
Requires-Dist: pytest-cov ; extra == 'test'
